dkstock/__init__.py
dkstock/stock/__init__.py
dkstock/stock/exchange.py
dkstock/stock/trading.py
dkstock-0.1.2.dist-info/WHEEL
dkstock-0.1.2.dist-info/METADATA
dkstock-0.1.2.dist-info/RECORD
