Metadata-Version: 2.1
Name: dkstock
Version: 0.1.2
Summary: python package
License: MIT
Author: czl8769
Author-email: dkkevincheng@outlook.com
Requires-Python: >=3.8,<4.0
Classifier: License :: OSI Approved :: MIT License
Classifier: Programming Language :: Python :: 3
Classifier: Programming Language :: Python :: 3.10
Classifier: Programming Language :: Python :: 3.8
Classifier: Programming Language :: Python :: 3.9
